prasanth/__init__.py
prasanth/neo4j_schema.py
prasanth-0.1.2.dist-info/licenses/LICENSE
prasanth-0.1.2.dist-info/METADATA
prasanth-0.1.2.dist-info/WHEEL
prasanth-0.1.2.dist-info/top_level.txt
prasanth-0.1.2.dist-info/RECORD
