Metadata-Version: 2.4
Name: prasanth
Version: 0.1.2
Summary: My first Python library!
Home-page: https://github.com/yourusername/prasanth
Author: Your Name
Author-email: your@email.com
Classifier: Programming Language :: Python :: 3
Classifier: License :: OSI Approved :: MIT License
Requires-Python: >=3.7
License-File: LICENSE
Dynamic: author
Dynamic: author-email
Dynamic: classifier
Dynamic: description-content-type
Dynamic: home-page
Dynamic: license-file
Dynamic: requires-python
Dynamic: summary
